files_handler/__init__.py
files_handler/folders_handler.py
files_handler/s3_handler.py
files_handler-0.2.1.dist-info/METADATA
files_handler-0.2.1.dist-info/WHEEL
files_handler-0.2.1.dist-info/top_level.txt
files_handler-0.2.1.dist-info/RECORD
